ILEE_CSK/ILEE_matlab_3D.m
ILEE_CSK/__init__.py
ILEE_CSK/fast_interp.py
ILEE_CSK/functions.py
ILEE_CSK/test_directory.m
ILEE_CSK-0.3.2.0.dist-info/LICENSE.txt
ILEE_CSK-0.3.2.0.dist-info/METADATA
ILEE_CSK-0.3.2.0.dist-info/WHEEL
ILEE_CSK-0.3.2.0.dist-info/top_level.txt
ILEE_CSK-0.3.2.0.dist-info/RECORD
