Metadata-Version: 2.1
Name: ILEE_CSK
Version: 0.3.2.0
Summary: A high-performance cytoskeleton image analysis platform
Author: Pai Li, Ze Zhang
License: MIT
License-File: LICENSE.txt
Requires-Dist: numpy
Requires-Dist: scikit-image
Requires-Dist: scikit-posthocs
Requires-Dist: scipy
Requires-Dist: pandas
Requires-Dist: skan
Requires-Dist: numba
Requires-Dist: seaborn
Requires-Dist: matplotlib
